src/__init__.py
src/config_parser.py
src/constants.py
src/containers.py
src/cpu.py
src/disks.py
src/exceptions.py
src/latency.py
src/main.py
src/memory.py
src/networking.py
src/processes.py
src/services.py
src/system.py
src/utils.py
pez_servermonitor-1.0.1.dist-info/LICENSE
pez_servermonitor-1.0.1.dist-info/METADATA
pez_servermonitor-1.0.1.dist-info/WHEEL
pez_servermonitor-1.0.1.dist-info/entry_points.txt
pez_servermonitor-1.0.1.dist-info/RECORD
